googling/__init__.py
googling/fun1.py
googling/main.py
googling/dist/__init__.py
googling/dist/fun1.py
googling/dist/googling.py
googling/dist/pytransform/__init__.py
googling/package/__init__.py
googling/package/fun2.py
googling/package/pytransform/__init__.py
googling/pytransform/__init__.py
googling-0.0.8.dist-info/METADATA
googling-0.0.8.dist-info/RECORD
googling-0.0.8.dist-info/WHEEL
googling-0.0.8.dist-info/top_level.txt
